README.md
setup.py
falcon_ask/__init__.py
falcon_ask/middleware.py
falcon_ask/util.py
falcon_ask.egg-info/PKG-INFO
falcon_ask.egg-info/SOURCES.txt
falcon_ask.egg-info/dependency_links.txt
falcon_ask.egg-info/requires.txt
falcon_ask.egg-info/top_level.txt