Metadata-Version: 2.1
Name: falcon-ask
Version: 1.1.1
Summary: Toolkit for writing Amazon Alexa skills in your Falcon app
Home-page: https://github.com/pvsune/falcon_ask
Author: Philamer Sune
Author-email: pvsune@hotmail.com
License: ISC
Platform: UNKNOWN
Classifier: Development Status :: 4 - Beta
Classifier: Intended Audience :: Developers
Classifier: License :: OSI Approved :: ISC License (ISCL)
Classifier: Programming Language :: Python :: 3.5
Classifier: Topic :: Home Automation
Classifier: Topic :: Internet :: WWW/HTTP :: WSGI :: Application
Classifier: Topic :: Software Development :: Libraries :: Application Frameworks
